{
	"meshinfo" : 
	[
		{
			"affine" : 
			[
				[ 1.0, 0.0, 0.0, 0.0 ],
				[ 0.0, 1.0, 0.0, 0.0 ],
				[ 0.0, 0.0, 1.0, 0.0 ],
				[ 0.0, 0.0, 0.0, 1.0 ]
			],
			"color" : 
			[
				{
					"alpha" : 1.0,
					"blue" : 0.64882946014404297,
					"green" : 0.37391278147697449,
					"red" : 0.27341976761817932
				},
				{
					"alpha" : 1.0,
					"blue" : 0.87290966510772705,
					"green" : 0.47535350918769836,
					"red" : 0.34449279308319092
				},
				{
					"alpha" : 1.0,
					"blue" : 0.80602008104324341,
					"green" : 0.38952651619911194,
					"red" : 0.266876220703125
				},
				{
					"alpha" : 1.0,
					"blue" : 0.67892980575561523,
					"green" : 0.27753075957298279,
					"red" : 0.27475085854530334
				},
				{
					"alpha" : 1.0,
					"blue" : 0.52173912525177002,
					"green" : 0.23002453148365021,
					"red" : 0.20066888630390167
				},
				{
					"alpha" : 0.0,
					"blue" : 0.0,
					"green" : 0.0,
					"red" : 0.0
				},
				{
					"alpha" : 0.0,
					"blue" : 0.0,
					"green" : 0.0,
					"red" : 0.0
				},
				{
					"alpha" : 0.0,
					"blue" : 0.0,
					"green" : 0.0,
					"red" : 0.0
				},
				{
					"alpha" : 0.0,
					"blue" : 0.0,
					"green" : 0.0,
					"red" : 0.0
				},
				{
					"alpha" : 0.0,
					"blue" : 0.0,
					"green" : 0.0,
					"red" : 0.0
				},
				{
					"alpha" : 0.0,
					"blue" : 0.0,
					"green" : 0.0,
					"red" : 0.0
				}
			],
			"meshpath" : "d",
			"name" : "Rect"
		}
	],
	"name" : "d",
	"version" : 2
}
